[
  {
    "Id": "Cajá",
    "Culinária": "Regional",
    "Gênero": "Todos os gêneros",
    "Público": "Grupos",
    "PetFriendly": "Sim",
    "Localização": "Rua Carneiro Vilela, 648-Aflitos, Recife-PE"
  },
  {
    "Id": "Zoco Café",
    "Culinária": "cafeteria",
    "Gênero": "Todos os gêneros",
    "Público": "Geral",
    "PetFriendly": "Sim",
    "Localização": ""
  },
  {
    "Id": "",
    "Culinária": "",
    "Gênero": "Todos os gêneros",
    "Público": "",
    "PetFriendly": "Sim",
    "Localização": ""
  },
  {
    "Id": "",
    "Culinária": "",
    "Gênero": "Todos os gêneros",
    "Público": "",
    "PetFriendly": "Sim",
    "Localização": ""
  }
]